Metadata-Version: 2.1
Name: QuakeScraper
Version: 0.1.1
Requires-Dist: beautifulsoup4
Requires-Dist: branca
Requires-Dist: certifi
Requires-Dist: charset-normalizer
Requires-Dist: folium
Requires-Dist: idna
Requires-Dist: Jinja2
Requires-Dist: MarkupSafe
Requires-Dist: numpy
Requires-Dist: pandas
Requires-Dist: python-dateutil
Requires-Dist: pytz
Requires-Dist: requests
Requires-Dist: six
Requires-Dist: urllib3
Requires-Dist: tzdata
